argsl/__init__.py
argsl/core.py
argsl-0.1.4.dist-info/licenses/LICENSE
argsl-0.1.4.dist-info/METADATA
argsl-0.1.4.dist-info/WHEEL
argsl-0.1.4.dist-info/entry_points.txt
argsl-0.1.4.dist-info/top_level.txt
argsl-0.1.4.dist-info/RECORD
