Metadata-Version: 2.4
Name: argsl
Version: 0.1.4
Summary: A convenience DSL layer over the `argparse` package.
Author-email: Gwang-Jin Kim <gwang.jin.kim.phd@gmail.com>
License: MIT
Requires-Python: >=3.8
License-File: LICENSE
Dynamic: license-file
